versionbumpr
