Metadata-Version: 2.1
Name: versionbumpr
Version: 1.0.1
Summary: Bump your setup.py's release version.
Home-page: https://github.com/jalavosus/versionbumpr
Author: jalavosus
Author-email: alavosus.james@gmail.com
License: MIT
Platform: UNKNOWN
